<?xml version="1.0" encoding="utf-8"?>
<resources>
    <style name="AppTheme" parent="Theme.AppCompat.Light.NoActionBar">
        <item name="colorPrimary">#0b2160</item>
        <item name="colorPrimaryDark">#040f26</item>
        <item name="colorAccent">#4a90d9</item>
        <item name="android:statusBarColor">#040f26</item>
        <item name="android:navigationBarColor">#040f26</item>
        <item name="android:windowBackground">#040f26</item>
        <item name="android:windowAnimationStyle">@null</item>
    </style>

    <style name="AppTheme.NoActionBar" parent="AppTheme">
        <item name="android:windowActionBar">false</item>
        <item name="android:windowNoTitle">true</item>
        <item name="android:windowFullscreen">true</item>
        <item name="android:windowContentOverlay">@null</item>
    </style>
</resources>
